swagger_render/__init__.py
swagger_render/exceptions.py
swagger_render/static/swagger_render/VERSION
swagger_render/static/swagger_render/favicon-16x16.png
swagger_render/static/swagger_render/favicon-32x32.png
swagger_render/static/swagger_render/oauth2-redirect.html
swagger_render/static/swagger_render/swagger-ui-bundle.js
swagger_render/static/swagger_render/swagger-ui-bundle.js.map
swagger_render/static/swagger_render/swagger-ui-standalone-preset.js
swagger_render/static/swagger_render/swagger-ui-standalone-preset.js.map
swagger_render/static/swagger_render/swagger-ui.css
swagger_render/static/swagger_render/swagger-ui.css.map
swagger_render/static/swagger_render/swagger-ui.js
swagger_render/static/swagger_render/swagger-ui.js.map
swagger_render/templates/swagger_render/index.html
swagger_render/views.py
django_swagger_render-0.1.1.dist-info/LICENSE
django_swagger_render-0.1.1.dist-info/WHEEL
django_swagger_render-0.1.1.dist-info/METADATA
django_swagger_render-0.1.1.dist-info/RECORD
