Metadata-Version: 2.1
Name: django-swagger-render
Version: 0.1.1
Summary: Swagger documentation in Django
Home-page: https://github.com/progremir/django-swagger-render
License: MIT
Author: Emir Amanbekov
Author-email: amanbekoff@gmail.com
Requires-Python: >=3.5,<4.0
Classifier: Environment :: Web Environment
Classifier: Framework :: Django
Classifier: Framework :: Django :: 2.0
Classifier: Framework :: Django :: 2.1
Classifier: Framework :: Django :: 2.2
Classifier: Intended Audience :: Developers
Classifier: License :: OSI Approved :: MIT License
Classifier: Programming Language :: Python
Classifier: Programming Language :: Python :: 3
Classifier: Programming Language :: Python :: 3 :: Only
Classifier: Programming Language :: Python :: 3.5
Classifier: Programming Language :: Python :: 3.6
Classifier: Programming Language :: Python :: 3.7
Classifier: Programming Language :: Python :: 3.8
Classifier: Topic :: Internet :: WWW/HTTP
Project-URL: Repository, https://github.com/progremir/django-swagger-render
